pi_lab_jupyter_extension/__init__.py
pi_lab_jupyter_extension/_version.py
pi_lab_jupyter_extension/auth.py
pi_lab_jupyter_extension/handlers/__init__.py
pi_lab_jupyter_extension/handlers/base_handler.py
pi_lab_jupyter_extension/handlers/course_handler.py
pi_lab_jupyter_extension/labextension/build_log.json
pi_lab_jupyter_extension/labextension/package.json
pi_lab_jupyter_extension/labextension/static/a5dd3bc133cc9f5d9a9170539c2f7dfec933b9ab7c02eeb7a761bbd97d22d3ff.gif
pi_lab_jupyter_extension/labextension/static/lib_index_js.056069c559b13fcb6d56.js
pi_lab_jupyter_extension/labextension/static/lib_index_js.056069c559b13fcb6d56.js.map
pi_lab_jupyter_extension/labextension/static/lib_index_js.05cbb272921d503a67e0.js
pi_lab_jupyter_extension/labextension/static/lib_index_js.05cbb272921d503a67e0.js.map
pi_lab_jupyter_extension/labextension/static/lib_index_js.0637592e4c2759596d8d.js
pi_lab_jupyter_extension/labextension/static/lib_index_js.0637592e4c2759596d8d.js.map
pi_lab_jupyter_extension/labextension/static/lib_index_js.0da0869ce3a21b36ba5e.js
pi_lab_jupyter_extension/labextension/static/lib_index_js.0da0869ce3a21b36ba5e.js.map
pi_lab_jupyter_extension/labextension/static/lib_index_js.0f8d1e8a36b72659db05.js
pi_lab_jupyter_extension/labextension/static/lib_index_js.0f8d1e8a36b72659db05.js.map
pi_lab_jupyter_extension/labextension/static/lib_index_js.10ee5107ac6bc40ad9c6.js
pi_lab_jupyter_extension/labextension/static/lib_index_js.10ee5107ac6bc40ad9c6.js.map
pi_lab_jupyter_extension/labextension/static/lib_index_js.1f3839c8e8f5dcf7d1b5.js
pi_lab_jupyter_extension/labextension/static/lib_index_js.1f3839c8e8f5dcf7d1b5.js.map
pi_lab_jupyter_extension/labextension/static/lib_index_js.21fc26a01fd96e2a41a2.js
pi_lab_jupyter_extension/labextension/static/lib_index_js.21fc26a01fd96e2a41a2.js.map
pi_lab_jupyter_extension/labextension/static/lib_index_js.232f6e5eddd2f64e0fe4.js
pi_lab_jupyter_extension/labextension/static/lib_index_js.232f6e5eddd2f64e0fe4.js.map
pi_lab_jupyter_extension-0.0.1.dist-info/METADATA
pi_lab_jupyter_extension-0.0.1.dist-info/WHEEL
pi_lab_jupyter_extension-0.0.1.dist-info/top_level.txt
pi_lab_jupyter_extension-0.0.1.dist-info/RECORD
